{
	"animations": [
		{
			"offsets": [
				-5,
				0
			],
			"loop": false,
			"fps": 24,
			"anim": "idle",
			"indices": [],
			"name": "idle"
		},
		{
			"offsets": [
				85,
				-51
			],
			"loop": false,
			"fps": 24,
			"anim": "singLEFT",
			"indices": [],
			"name": "left"
		},
		{
			"offsets": [
				-31,
				-92
			],
			"loop": false,
			"fps": 24,
			"anim": "singDOWN",
			"indices": [],
			"name": "down"
		},
		{
			"offsets": [
				3,
				55
			],
			"loop": false,
			"fps": 24,
			"anim": "singUP",
			"indices": [],
			"name": "up"
		},
		{
			"offsets": [
				1,
				-70
			],
			"loop": false,
			"fps": 24,
			"anim": "singRIGHT",
			"indices": [],
			"name": "right"
		}
	],
	"no_antialiasing": false,
	"image": "characters/doggo",
	"position": [
		350,
		-10
	],
	"healthicon": "dog icons",
	"flip_x": false,
	"healthbar_colors": [
		163,
		127,
		138
	],
	"camera_position": [
		70,
		370
	],
	"sing_duration": 4,
	"scale": 0.45
}